KKMeans.cp39-win_amd64.pyd
KKMeans/KKMeans.c
KKMeans/KKMeans.py
KKMeans/__init__.py
KKMeans/elkan.c
KKMeans/elkan.cp39-win_amd64.pyd
KKMeans/elkan.pyx
KKMeans/kernels.c
KKMeans/kernels.cp39-win_amd64.pyd
KKMeans/kernels.pyx
KKMeans/lloyd.c
KKMeans/lloyd.cp39-win_amd64.pyd
KKMeans/lloyd.pyx
KKMeans/quality.c
KKMeans/quality.cp39-win_amd64.pyd
KKMeans/quality.pyx
KKMeans/utils.c
KKMeans/utils.cp39-win_amd64.pyd
KKMeans/utils.pyx
KKMeans-0.1.0.dist-info/METADATA
KKMeans-0.1.0.dist-info/WHEEL
KKMeans-0.1.0.dist-info/license.txt
KKMeans-0.1.0.dist-info/top_level.txt
KKMeans-0.1.0.dist-info/RECORD
