Metadata-Version: 2.1
Name: KKMeans
Version: 0.1.0
Summary: https://github.com/bauxn/kernel-kmeans
Author-email: Paul Theis <keymailt7@gmail.com>
Project-URL: Thesis, https://github.com/bauxn/kernel-kmeans/blob/master/thesis_theis.pdf
Project-URL: Source, https://github.com/bauxn/kernel-kmeans
Classifier: License :: OSI Approved :: MIT License
Requires-Python: >=3.9
License-File: license.txt
Requires-Dist: numpy >=1.25
